scansegmentdecoding/__init__.py
scansegmentdecoding/connectionHandler.py
scansegmentdecoding/decodeUtil.py
scansegmentdecoding/msgpackUtil.py
scansegmentdecoding-2.0.4.dist-info/LICENSE
scansegmentdecoding-2.0.4.dist-info/METADATA
scansegmentdecoding-2.0.4.dist-info/WHEEL
scansegmentdecoding-2.0.4.dist-info/RECORD
