Metadata-Version: 2.1
Name: scansegmentdecoding
Version: 2.0.4
Summary: 
Author: Johannes Albrecht
Requires-Python: >=3.9,<4.0
Classifier: Programming Language :: Python :: 3
Classifier: Programming Language :: Python :: 3.9
Classifier: Programming Language :: Python :: 3.10
Classifier: Programming Language :: Python :: 3.11
Requires-Dist: msgpack (>=1.0.3,<2.0.0)
Requires-Dist: numpy (>=1.23.0,<2.0.0)
Requires-Dist: requests (>=2.27.1,<3.0.0)
